[
    {
        "site": "Flex Jobs",
        "host": "flexjobs.com/",
        "board_selectors": {
            "link_selector": "test"
        }
    },
    {
        "site": "We Work Remotely",
        "host": "weworkremotely.com/",
        "board_selectors": {
            "link_selector": "li.new-listing-container > a[href^='/listings/']"
        }
    },
    {
        "site": "Empollo",
        "host": "empllo.com/",
        "board_selectors": {
            "link_selector": "test"
        }
    }
]